appshwnd/LICENSE
appshwnd/README.md
appshwnd/__init__.py
appshwnd/requirements.txt
appshwnd/thirdparty.json
appshwnd-0.11.dist-info/LICENSE.rst
appshwnd-0.11.dist-info/METADATA
appshwnd-0.11.dist-info/WHEEL
appshwnd-0.11.dist-info/top_level.txt
appshwnd-0.11.dist-info/RECORD
