Metadata-Version: 2.1
Name: appshwnd
Version: 0.11
Summary: includes functions for finding windows based on various attributes, getting information about visible and invisible windows, and making window names unique
Home-page: https://github.com/hansalemaos/appshwnd
Author: Johannes Fischer
Author-email: aulasparticularesdealemaosp@gmail.com
License: MIT
Keywords: ctypes,hwnd,search,windows
Classifier: Development Status :: 4 - Beta
Classifier: Programming Language :: Python :: 3 :: Only
Classifier: Programming Language :: Python :: 3.10
Classifier: Topic :: Software Development :: Libraries :: Python Modules
Classifier: Topic :: Utilities
License-File: LICENSE.rst
Requires-Dist: ctypes-window-info
Requires-Dist: flexible-partial
